easy_as_pypi_termio/__init__.py
easy_as_pypi_termio/ascii_art.py
easy_as_pypi_termio/ascii_table.py
easy_as_pypi_termio/crude_progress.py
easy_as_pypi_termio/echoes.py
easy_as_pypi_termio/errors.py
easy_as_pypi_termio/paging.py
easy_as_pypi_termio/style.py
easy_as_pypi_termio-1.0.4.dist-info/LICENSE
easy_as_pypi_termio-1.0.4.dist-info/METADATA
easy_as_pypi_termio-1.0.4.dist-info/WHEEL
easy_as_pypi_termio-1.0.4.dist-info/RECORD
